{
  "@context": "https://iiif.io/api/presentation/3/context.json",
  "id": "https://nulib-ds.github.io/muybridge/iiif/plate-number-77-ascending-an-incline.json",
  "type": "Manifest",
  "label": {
    "en": [
      "Plate Number 77. Ascending an incline"
    ]
  },
  "behavior": [
    "repeat",
    "auto-advance"
  ],
  "metadata": [
    {
      "label": {
        "en": [
          "Date"
        ]
      },
      "value": {
        "en": [
          "1887"
        ]
      }
    },
    {
      "label": {
        "en": [
          "Plate Number"
        ]
      },
      "value": {
        "en": [
          "77"
        ]
      }
    },
    {
      "label": {
        "en": [
          "Frames"
        ]
      },
      "value": {
        "en": [
          "36"
        ]
      }
    },
    {
      "label": {
        "en": [
          "Provider"
        ]
      },
      "value": {
        "en": [
          "National Gallery of Art"
        ]
      }
    }
  ],
  "thumbnail": [
    {
      "id": "https://fantastic-adventure-v3pgm1o.pages.github.io/images/thumbnails/plate-number-77-ascending-an-incline.gif",
      "type": "Image",
      "format": "image/gif"
    }
  ],
  "items": [
    {
      "id": "https://nulib-ds.github.io/muybridge/iiif/plate-number-77-ascending-an-incline.json/canvas/animation",
      "type": "Canvas",
      "label": {
        "en": [
          "Plate Number 77. Ascending an incline"
        ]
      },
      "height": 745,
      "width": 296,
      "duration": 3.6,
      "placeholderCanvas": {
        "id": "https://nulib-ds.github.io/muybridge/iiif/plate-number-77-ascending-an-incline.json/canvas/animation/placeholder",
        "type": "Canvas",
        "width": 296,
        "height": 745,
        "items": [
          {
            "id": "https://nulib-ds.github.io/muybridge/iiif/plate-number-77-ascending-an-incline.json/canvas/animation/placeholder/page/1",
            "type": "AnnotationPage",
            "items": [
              {
                "id": "https://nulib-ds.github.io/muybridge/iiif/plate-number-77-ascending-an-incline.json/canvas/animation/placeholder/page/1/annotation/1",
                "type": "Annotation",
                "motivation": "painting",
                "body": {
                  "id": "https://fantastic-adventure-v3pgm1o.pages.github.io/images/thumbnails/plate-number-77-ascending-an-incline.gif",
                  "type": "Image",
                  "format": "image/gif",
                  "width": 296,
                  "height": 745
                },
                "target": "https://nulib-ds.github.io/muybridge/iiif/plate-number-77-ascending-an-incline.json/canvas/animation/placeholder"
              }
            ]
          }
        ]
      },
      "items": [
        {
          "id": "https://nulib-ds.github.io/muybridge/iiif/plate-number-77-ascending-an-incline.json/canvas/animation/page/1",
          "type": "AnnotationPage",
          "items": [
            {
              "id": "https://nulib-ds.github.io/muybridge/iiif/plate-number-77-ascending-an-incline.json/canvas/animation/page/1/annotation/1",
              "type": "Annotation",
              "motivation": "painting",
              "label": {
                "en": [
                  "1"
                ]
              },
              "body": {
                "id": "https://api.nga.gov/iiif/63eb96e1-8e5e-46b8-99ba-822824225e86/pct:1.1298,2.0538,7.7697,34.7011/full/0/default.jpg",
                "type": "Image",
                "format": "image/jpeg",
                "height": 745,
                "width": 296
              },
              "target": "https://nulib-ds.github.io/muybridge/iiif/plate-number-77-ascending-an-incline.json/canvas/animation#t=0,0.1"
            },
            {
              "id": "https://nulib-ds.github.io/muybridge/iiif/plate-number-77-ascending-an-incline.json/canvas/animation/page/1/annotation/2",
              "type": "Annotation",
              "motivation": "painting",
              "label": {
                "en": [
                  "2"
                ]
              },
              "body": {
                "id": "https://api.nga.gov/iiif/63eb96e1-8e5e-46b8-99ba-822824225e86/pct:9.0306,2.0538,7.7697,34.7011/full/0/default.jpg",
                "type": "Image",
                "format": "image/jpeg",
                "height": 745,
                "width": 296
              },
              "target": "https://nulib-ds.github.io/muybridge/iiif/plate-number-77-ascending-an-incline.json/canvas/animation#t=0.1,0.2"
            },
            {
              "id": "https://nulib-ds.github.io/muybridge/iiif/plate-number-77-ascending-an-incline.json/canvas/animation/page/1/annotation/3",
              "type": "Annotation",
              "motivation": "painting",
              "label": {
                "en": [
                  "3"
                ]
              },
              "body": {
                "id": "https://api.nga.gov/iiif/63eb96e1-8e5e-46b8-99ba-822824225e86/pct:16.9314,2.0538,7.7697,34.7011/full/0/default.jpg",
                "type": "Image",
                "format": "image/jpeg",
                "height": 745,
                "width": 296
              },
              "target": "https://nulib-ds.github.io/muybridge/iiif/plate-number-77-ascending-an-incline.json/canvas/animation#t=0.2,0.3"
            },
            {
              "id": "https://nulib-ds.github.io/muybridge/iiif/plate-number-77-ascending-an-incline.json/canvas/animation/page/1/annotation/4",
              "type": "Annotation",
              "motivation": "painting",
              "label": {
                "en": [
                  "4"
                ]
              },
              "body": {
                "id": "https://api.nga.gov/iiif/63eb96e1-8e5e-46b8-99ba-822824225e86/pct:24.8323,2.0538,7.7697,34.7011/full/0/default.jpg",
                "type": "Image",
                "format": "image/jpeg",
                "height": 745,
                "width": 296
              },
              "target": "https://nulib-ds.github.io/muybridge/iiif/plate-number-77-ascending-an-incline.json/canvas/animation#t=0.3,0.4"
            },
            {
              "id": "https://nulib-ds.github.io/muybridge/iiif/plate-number-77-ascending-an-incline.json/canvas/animation/page/1/annotation/5",
              "type": "Annotation",
              "motivation": "painting",
              "label": {
                "en": [
                  "5"
                ]
              },
              "body": {
                "id": "https://api.nga.gov/iiif/63eb96e1-8e5e-46b8-99ba-822824225e86/pct:32.7331,2.0538,7.7697,34.7011/full/0/default.jpg",
                "type": "Image",
                "format": "image/jpeg",
                "height": 745,
                "width": 296
              },
              "target": "https://nulib-ds.github.io/muybridge/iiif/plate-number-77-ascending-an-incline.json/canvas/animation#t=0.4,0.5"
            },
            {
              "id": "https://nulib-ds.github.io/muybridge/iiif/plate-number-77-ascending-an-incline.json/canvas/animation/page/1/annotation/6",
              "type": "Annotation",
              "motivation": "painting",
              "label": {
                "en": [
                  "6"
                ]
              },
              "body": {
                "id": "https://api.nga.gov/iiif/63eb96e1-8e5e-46b8-99ba-822824225e86/pct:40.6339,2.0538,7.7697,34.7011/full/0/default.jpg",
                "type": "Image",
                "format": "image/jpeg",
                "height": 745,
                "width": 296
              },
              "target": "https://nulib-ds.github.io/muybridge/iiif/plate-number-77-ascending-an-incline.json/canvas/animation#t=0.5,0.6"
            },
            {
              "id": "https://nulib-ds.github.io/muybridge/iiif/plate-number-77-ascending-an-incline.json/canvas/animation/page/1/annotation/7",
              "type": "Annotation",
              "motivation": "painting",
              "label": {
                "en": [
                  "7"
                ]
              },
              "body": {
                "id": "https://api.nga.gov/iiif/63eb96e1-8e5e-46b8-99ba-822824225e86/pct:48.5348,2.0538,7.7697,34.7011/full/0/default.jpg",
                "type": "Image",
                "format": "image/jpeg",
                "height": 745,
                "width": 296
              },
              "target": "https://nulib-ds.github.io/muybridge/iiif/plate-number-77-ascending-an-incline.json/canvas/animation#t=0.6,0.7"
            },
            {
              "id": "https://nulib-ds.github.io/muybridge/iiif/plate-number-77-ascending-an-incline.json/canvas/animation/page/1/annotation/8",
              "type": "Annotation",
              "motivation": "painting",
              "label": {
                "en": [
                  "8"
                ]
              },
              "body": {
                "id": "https://api.nga.gov/iiif/63eb96e1-8e5e-46b8-99ba-822824225e86/pct:56.4356,2.0538,7.7697,34.7011/full/0/default.jpg",
                "type": "Image",
                "format": "image/jpeg",
                "height": 745,
                "width": 296
              },
              "target": "https://nulib-ds.github.io/muybridge/iiif/plate-number-77-ascending-an-incline.json/canvas/animation#t=0.7,0.8"
            },
            {
              "id": "https://nulib-ds.github.io/muybridge/iiif/plate-number-77-ascending-an-incline.json/canvas/animation/page/1/annotation/9",
              "type": "Annotation",
              "motivation": "painting",
              "label": {
                "en": [
                  "9"
                ]
              },
              "body": {
                "id": "https://api.nga.gov/iiif/63eb96e1-8e5e-46b8-99ba-822824225e86/pct:64.3364,2.0538,7.7697,34.7011/full/0/default.jpg",
                "type": "Image",
                "format": "image/jpeg",
                "height": 745,
                "width": 296
              },
              "target": "https://nulib-ds.github.io/muybridge/iiif/plate-number-77-ascending-an-incline.json/canvas/animation#t=0.8,0.9"
            },
            {
              "id": "https://nulib-ds.github.io/muybridge/iiif/plate-number-77-ascending-an-incline.json/canvas/animation/page/1/annotation/10",
              "type": "Annotation",
              "motivation": "painting",
              "label": {
                "en": [
                  "10"
                ]
              },
              "body": {
                "id": "https://api.nga.gov/iiif/63eb96e1-8e5e-46b8-99ba-822824225e86/pct:72.2373,2.0538,7.7697,34.7011/full/0/default.jpg",
                "type": "Image",
                "format": "image/jpeg",
                "height": 745,
                "width": 296
              },
              "target": "https://nulib-ds.github.io/muybridge/iiif/plate-number-77-ascending-an-incline.json/canvas/animation#t=0.9,1"
            },
            {
              "id": "https://nulib-ds.github.io/muybridge/iiif/plate-number-77-ascending-an-incline.json/canvas/animation/page/1/annotation/11",
              "type": "Annotation",
              "motivation": "painting",
              "label": {
                "en": [
                  "11"
                ]
              },
              "body": {
                "id": "https://api.nga.gov/iiif/63eb96e1-8e5e-46b8-99ba-822824225e86/pct:80.1381,2.0538,7.7697,34.7011/full/0/default.jpg",
                "type": "Image",
                "format": "image/jpeg",
                "height": 745,
                "width": 296
              },
              "target": "https://nulib-ds.github.io/muybridge/iiif/plate-number-77-ascending-an-incline.json/canvas/animation#t=1,1.1"
            },
            {
              "id": "https://nulib-ds.github.io/muybridge/iiif/plate-number-77-ascending-an-incline.json/canvas/animation/page/1/annotation/12",
              "type": "Annotation",
              "motivation": "painting",
              "label": {
                "en": [
                  "12"
                ]
              },
              "body": {
                "id": "https://api.nga.gov/iiif/63eb96e1-8e5e-46b8-99ba-822824225e86/pct:88.0389,2.0538,7.7697,34.7011/full/0/default.jpg",
                "type": "Image",
                "format": "image/jpeg",
                "height": 745,
                "width": 296
              },
              "target": "https://nulib-ds.github.io/muybridge/iiif/plate-number-77-ascending-an-incline.json/canvas/animation#t=1.1,1.2"
            },
            {
              "id": "https://nulib-ds.github.io/muybridge/iiif/plate-number-77-ascending-an-incline.json/canvas/animation/page/1/annotation/13",
              "type": "Annotation",
              "motivation": "painting",
              "label": {
                "en": [
                  "13"
                ]
              },
              "body": {
                "id": "https://api.nga.gov/iiif/63eb96e1-8e5e-46b8-99ba-822824225e86/pct:1.2091,38.5498,7.7697,29.8092/full/0/default.jpg",
                "type": "Image",
                "format": "image/jpeg",
                "height": 640,
                "width": 296
              },
              "target": "https://nulib-ds.github.io/muybridge/iiif/plate-number-77-ascending-an-incline.json/canvas/animation#t=1.2,1.3"
            },
            {
              "id": "https://nulib-ds.github.io/muybridge/iiif/plate-number-77-ascending-an-incline.json/canvas/animation/page/1/annotation/14",
              "type": "Annotation",
              "motivation": "painting",
              "label": {
                "en": [
                  "14"
                ]
              },
              "body": {
                "id": "https://api.nga.gov/iiif/63eb96e1-8e5e-46b8-99ba-822824225e86/pct:9.2410,38.5498,7.7697,29.8092/full/0/default.jpg",
                "type": "Image",
                "format": "image/jpeg",
                "height": 640,
                "width": 296
              },
              "target": "https://nulib-ds.github.io/muybridge/iiif/plate-number-77-ascending-an-incline.json/canvas/animation#t=1.3,1.4"
            },
            {
              "id": "https://nulib-ds.github.io/muybridge/iiif/plate-number-77-ascending-an-incline.json/canvas/animation/page/1/annotation/15",
              "type": "Annotation",
              "motivation": "painting",
              "label": {
                "en": [
                  "15"
                ]
              },
              "body": {
                "id": "https://api.nga.gov/iiif/63eb96e1-8e5e-46b8-99ba-822824225e86/pct:17.2729,38.5498,7.7697,29.8092/full/0/default.jpg",
                "type": "Image",
                "format": "image/jpeg",
                "height": 640,
                "width": 296
              },
              "target": "https://nulib-ds.github.io/muybridge/iiif/plate-number-77-ascending-an-incline.json/canvas/animation#t=1.4,1.5"
            },
            {
              "id": "https://nulib-ds.github.io/muybridge/iiif/plate-number-77-ascending-an-incline.json/canvas/animation/page/1/annotation/16",
              "type": "Annotation",
              "motivation": "painting",
              "label": {
                "en": [
                  "16"
                ]
              },
              "body": {
                "id": "https://api.nga.gov/iiif/63eb96e1-8e5e-46b8-99ba-822824225e86/pct:25.3048,38.5498,7.7697,29.8092/full/0/default.jpg",
                "type": "Image",
                "format": "image/jpeg",
                "height": 640,
                "width": 296
              },
              "target": "https://nulib-ds.github.io/muybridge/iiif/plate-number-77-ascending-an-incline.json/canvas/animation#t=1.5,1.6"
            },
            {
              "id": "https://nulib-ds.github.io/muybridge/iiif/plate-number-77-ascending-an-incline.json/canvas/animation/page/1/annotation/17",
              "type": "Annotation",
              "motivation": "painting",
              "label": {
                "en": [
                  "17"
                ]
              },
              "body": {
                "id": "https://api.nga.gov/iiif/63eb96e1-8e5e-46b8-99ba-822824225e86/pct:33.3368,38.5498,7.7697,29.8092/full/0/default.jpg",
                "type": "Image",
                "format": "image/jpeg",
                "height": 640,
                "width": 296
              },
              "target": "https://nulib-ds.github.io/muybridge/iiif/plate-number-77-ascending-an-incline.json/canvas/animation#t=1.6,1.7"
            },
            {
              "id": "https://nulib-ds.github.io/muybridge/iiif/plate-number-77-ascending-an-incline.json/canvas/animation/page/1/annotation/18",
              "type": "Annotation",
              "motivation": "painting",
              "label": {
                "en": [
                  "18"
                ]
              },
              "body": {
                "id": "https://api.nga.gov/iiif/63eb96e1-8e5e-46b8-99ba-822824225e86/pct:41.3687,38.5498,7.7697,29.8092/full/0/default.jpg",
                "type": "Image",
                "format": "image/jpeg",
                "height": 640,
                "width": 296
              },
              "target": "https://nulib-ds.github.io/muybridge/iiif/plate-number-77-ascending-an-incline.json/canvas/animation#t=1.7,1.8"
            },
            {
              "id": "https://nulib-ds.github.io/muybridge/iiif/plate-number-77-ascending-an-incline.json/canvas/animation/page/1/annotation/19",
              "type": "Annotation",
              "motivation": "painting",
              "label": {
                "en": [
                  "19"
                ]
              },
              "body": {
                "id": "https://api.nga.gov/iiif/63eb96e1-8e5e-46b8-99ba-822824225e86/pct:49.4006,38.5498,7.7697,29.8092/full/0/default.jpg",
                "type": "Image",
                "format": "image/jpeg",
                "height": 640,
                "width": 296
              },
              "target": "https://nulib-ds.github.io/muybridge/iiif/plate-number-77-ascending-an-incline.json/canvas/animation#t=1.8,1.9"
            },
            {
              "id": "https://nulib-ds.github.io/muybridge/iiif/plate-number-77-ascending-an-incline.json/canvas/animation/page/1/annotation/20",
              "type": "Annotation",
              "motivation": "painting",
              "label": {
                "en": [
                  "20"
                ]
              },
              "body": {
                "id": "https://api.nga.gov/iiif/63eb96e1-8e5e-46b8-99ba-822824225e86/pct:57.4326,38.5498,7.7697,29.8092/full/0/default.jpg",
                "type": "Image",
                "format": "image/jpeg",
                "height": 640,
                "width": 296
              },
              "target": "https://nulib-ds.github.io/muybridge/iiif/plate-number-77-ascending-an-incline.json/canvas/animation#t=1.9,2"
            },
            {
              "id": "https://nulib-ds.github.io/muybridge/iiif/plate-number-77-ascending-an-incline.json/canvas/animation/page/1/annotation/21",
              "type": "Annotation",
              "motivation": "painting",
              "label": {
                "en": [
                  "21"
                ]
              },
              "body": {
                "id": "https://api.nga.gov/iiif/63eb96e1-8e5e-46b8-99ba-822824225e86/pct:65.4645,38.5498,7.7697,29.8092/full/0/default.jpg",
                "type": "Image",
                "format": "image/jpeg",
                "height": 640,
                "width": 296
              },
              "target": "https://nulib-ds.github.io/muybridge/iiif/plate-number-77-ascending-an-incline.json/canvas/animation#t=2,2.1"
            },
            {
              "id": "https://nulib-ds.github.io/muybridge/iiif/plate-number-77-ascending-an-incline.json/canvas/animation/page/1/annotation/22",
              "type": "Annotation",
              "motivation": "painting",
              "label": {
                "en": [
                  "22"
                ]
              },
              "body": {
                "id": "https://api.nga.gov/iiif/63eb96e1-8e5e-46b8-99ba-822824225e86/pct:73.4964,38.5498,7.7697,29.8092/full/0/default.jpg",
                "type": "Image",
                "format": "image/jpeg",
                "height": 640,
                "width": 296
              },
              "target": "https://nulib-ds.github.io/muybridge/iiif/plate-number-77-ascending-an-incline.json/canvas/animation#t=2.1,2.2"
            },
            {
              "id": "https://nulib-ds.github.io/muybridge/iiif/plate-number-77-ascending-an-incline.json/canvas/animation/page/1/annotation/23",
              "type": "Annotation",
              "motivation": "painting",
              "label": {
                "en": [
                  "23"
                ]
              },
              "body": {
                "id": "https://api.nga.gov/iiif/63eb96e1-8e5e-46b8-99ba-822824225e86/pct:81.5283,38.5498,7.7697,29.8092/full/0/default.jpg",
                "type": "Image",
                "format": "image/jpeg",
                "height": 640,
                "width": 296
              },
              "target": "https://nulib-ds.github.io/muybridge/iiif/plate-number-77-ascending-an-incline.json/canvas/animation#t=2.2,2.3"
            },
            {
              "id": "https://nulib-ds.github.io/muybridge/iiif/plate-number-77-ascending-an-incline.json/canvas/animation/page/1/annotation/24",
              "type": "Annotation",
              "motivation": "painting",
              "label": {
                "en": [
                  "24"
                ]
              },
              "body": {
                "id": "https://api.nga.gov/iiif/63eb96e1-8e5e-46b8-99ba-822824225e86/pct:89.5603,38.5498,7.7697,29.8092/full/0/default.jpg",
                "type": "Image",
                "format": "image/jpeg",
                "height": 640,
                "width": 296
              },
              "target": "https://nulib-ds.github.io/muybridge/iiif/plate-number-77-ascending-an-incline.json/canvas/animation#t=2.3,2.4"
            },
            {
              "id": "https://nulib-ds.github.io/muybridge/iiif/plate-number-77-ascending-an-incline.json/canvas/animation/page/1/annotation/25",
              "type": "Annotation",
              "motivation": "painting",
              "label": {
                "en": [
                  "25"
                ]
              },
              "body": {
                "id": "https://api.nga.gov/iiif/63eb96e1-8e5e-46b8-99ba-822824225e86/pct:1.3478,70.5410,7.8490,27.9791/full/0/default.jpg",
                "type": "Image",
                "format": "image/jpeg",
                "height": 601,
                "width": 299
              },
              "target": "https://nulib-ds.github.io/muybridge/iiif/plate-number-77-ascending-an-incline.json/canvas/animation#t=2.4,2.5"
            },
            {
              "id": "https://nulib-ds.github.io/muybridge/iiif/plate-number-77-ascending-an-incline.json/canvas/animation/page/1/annotation/26",
              "type": "Annotation",
              "motivation": "painting",
              "label": {
                "en": [
                  "26"
                ]
              },
              "body": {
                "id": "https://api.nga.gov/iiif/63eb96e1-8e5e-46b8-99ba-822824225e86/pct:9.4590,70.5410,7.8490,27.9791/full/0/default.jpg",
                "type": "Image",
                "format": "image/jpeg",
                "height": 601,
                "width": 299
              },
              "target": "https://nulib-ds.github.io/muybridge/iiif/plate-number-77-ascending-an-incline.json/canvas/animation#t=2.5,2.6"
            },
            {
              "id": "https://nulib-ds.github.io/muybridge/iiif/plate-number-77-ascending-an-incline.json/canvas/animation/page/1/annotation/27",
              "type": "Annotation",
              "motivation": "painting",
              "label": {
                "en": [
                  "27"
                ]
              },
              "body": {
                "id": "https://api.nga.gov/iiif/63eb96e1-8e5e-46b8-99ba-822824225e86/pct:17.5702,70.5410,7.8490,27.9791/full/0/default.jpg",
                "type": "Image",
                "format": "image/jpeg",
                "height": 601,
                "width": 299
              },
              "target": "https://nulib-ds.github.io/muybridge/iiif/plate-number-77-ascending-an-incline.json/canvas/animation#t=2.6,2.7"
            },
            {
              "id": "https://nulib-ds.github.io/muybridge/iiif/plate-number-77-ascending-an-incline.json/canvas/animation/page/1/annotation/28",
              "type": "Annotation",
              "motivation": "painting",
              "label": {
                "en": [
                  "28"
                ]
              },
              "body": {
                "id": "https://api.nga.gov/iiif/63eb96e1-8e5e-46b8-99ba-822824225e86/pct:25.6814,70.5410,7.8490,27.9791/full/0/default.jpg",
                "type": "Image",
                "format": "image/jpeg",
                "height": 601,
                "width": 299
              },
              "target": "https://nulib-ds.github.io/muybridge/iiif/plate-number-77-ascending-an-incline.json/canvas/animation#t=2.7,2.8"
            },
            {
              "id": "https://nulib-ds.github.io/muybridge/iiif/plate-number-77-ascending-an-incline.json/canvas/animation/page/1/annotation/29",
              "type": "Annotation",
              "motivation": "painting",
              "label": {
                "en": [
                  "29"
                ]
              },
              "body": {
                "id": "https://api.nga.gov/iiif/63eb96e1-8e5e-46b8-99ba-822824225e86/pct:33.7926,70.5410,7.8490,27.9791/full/0/default.jpg",
                "type": "Image",
                "format": "image/jpeg",
                "height": 601,
                "width": 299
              },
              "target": "https://nulib-ds.github.io/muybridge/iiif/plate-number-77-ascending-an-incline.json/canvas/animation#t=2.8,2.9"
            },
            {
              "id": "https://nulib-ds.github.io/muybridge/iiif/plate-number-77-ascending-an-incline.json/canvas/animation/page/1/annotation/30",
              "type": "Annotation",
              "motivation": "painting",
              "label": {
                "en": [
                  "30"
                ]
              },
              "body": {
                "id": "https://api.nga.gov/iiif/63eb96e1-8e5e-46b8-99ba-822824225e86/pct:41.9039,70.5410,7.8490,27.9791/full/0/default.jpg",
                "type": "Image",
                "format": "image/jpeg",
                "height": 601,
                "width": 299
              },
              "target": "https://nulib-ds.github.io/muybridge/iiif/plate-number-77-ascending-an-incline.json/canvas/animation#t=2.9,3"
            },
            {
              "id": "https://nulib-ds.github.io/muybridge/iiif/plate-number-77-ascending-an-incline.json/canvas/animation/page/1/annotation/31",
              "type": "Annotation",
              "motivation": "painting",
              "label": {
                "en": [
                  "31"
                ]
              },
              "body": {
                "id": "https://api.nga.gov/iiif/63eb96e1-8e5e-46b8-99ba-822824225e86/pct:50.0151,70.5410,7.8490,27.9791/full/0/default.jpg",
                "type": "Image",
                "format": "image/jpeg",
                "height": 601,
                "width": 299
              },
              "target": "https://nulib-ds.github.io/muybridge/iiif/plate-number-77-ascending-an-incline.json/canvas/animation#t=3,3.1"
            },
            {
              "id": "https://nulib-ds.github.io/muybridge/iiif/plate-number-77-ascending-an-incline.json/canvas/animation/page/1/annotation/32",
              "type": "Annotation",
              "motivation": "painting",
              "label": {
                "en": [
                  "32"
                ]
              },
              "body": {
                "id": "https://api.nga.gov/iiif/63eb96e1-8e5e-46b8-99ba-822824225e86/pct:58.1263,70.5410,7.8490,27.9791/full/0/default.jpg",
                "type": "Image",
                "format": "image/jpeg",
                "height": 601,
                "width": 299
              },
              "target": "https://nulib-ds.github.io/muybridge/iiif/plate-number-77-ascending-an-incline.json/canvas/animation#t=3.1,3.2"
            },
            {
              "id": "https://nulib-ds.github.io/muybridge/iiif/plate-number-77-ascending-an-incline.json/canvas/animation/page/1/annotation/33",
              "type": "Annotation",
              "motivation": "painting",
              "label": {
                "en": [
                  "33"
                ]
              },
              "body": {
                "id": "https://api.nga.gov/iiif/63eb96e1-8e5e-46b8-99ba-822824225e86/pct:66.2375,70.5410,7.8490,27.9791/full/0/default.jpg",
                "type": "Image",
                "format": "image/jpeg",
                "height": 601,
                "width": 299
              },
              "target": "https://nulib-ds.github.io/muybridge/iiif/plate-number-77-ascending-an-incline.json/canvas/animation#t=3.2,3.3"
            },
            {
              "id": "https://nulib-ds.github.io/muybridge/iiif/plate-number-77-ascending-an-incline.json/canvas/animation/page/1/annotation/34",
              "type": "Annotation",
              "motivation": "painting",
              "label": {
                "en": [
                  "34"
                ]
              },
              "body": {
                "id": "https://api.nga.gov/iiif/63eb96e1-8e5e-46b8-99ba-822824225e86/pct:74.3487,70.5410,7.8490,27.9791/full/0/default.jpg",
                "type": "Image",
                "format": "image/jpeg",
                "height": 601,
                "width": 299
              },
              "target": "https://nulib-ds.github.io/muybridge/iiif/plate-number-77-ascending-an-incline.json/canvas/animation#t=3.3,3.4"
            },
            {
              "id": "https://nulib-ds.github.io/muybridge/iiif/plate-number-77-ascending-an-incline.json/canvas/animation/page/1/annotation/35",
              "type": "Annotation",
              "motivation": "painting",
              "label": {
                "en": [
                  "35"
                ]
              },
              "body": {
                "id": "https://api.nga.gov/iiif/63eb96e1-8e5e-46b8-99ba-822824225e86/pct:82.4599,70.5410,7.8490,27.9791/full/0/default.jpg",
                "type": "Image",
                "format": "image/jpeg",
                "height": 601,
                "width": 299
              },
              "target": "https://nulib-ds.github.io/muybridge/iiif/plate-number-77-ascending-an-incline.json/canvas/animation#t=3.4,3.5"
            },
            {
              "id": "https://nulib-ds.github.io/muybridge/iiif/plate-number-77-ascending-an-incline.json/canvas/animation/page/1/annotation/36",
              "type": "Annotation",
              "motivation": "painting",
              "label": {
                "en": [
                  "36"
                ]
              },
              "body": {
                "id": "https://api.nga.gov/iiif/63eb96e1-8e5e-46b8-99ba-822824225e86/pct:90.5711,70.5410,7.8490,27.9791/full/0/default.jpg",
                "type": "Image",
                "format": "image/jpeg",
                "height": 601,
                "width": 299
              },
              "target": "https://nulib-ds.github.io/muybridge/iiif/plate-number-77-ascending-an-incline.json/canvas/animation#t=3.5,3.6"
            }
          ]
        }
      ]
    },
    {
      "id": "https://nulib-ds.github.io/muybridge/iiif/plate-number-77-ascending-an-incline.json/canvas/static",
      "type": "Canvas",
      "label": {
        "en": [
          "Plate Number 77. Ascending an incline"
        ]
      },
      "height": 2148,
      "width": 3814,
      "placeholderCanvas": {
        "id": "https://nulib-ds.github.io/muybridge/iiif/plate-number-77-ascending-an-incline.json/canvas/static/placeholder",
        "type": "Canvas",
        "width": 800,
        "height": 451,
        "items": [
          {
            "id": "https://nulib-ds.github.io/muybridge/iiif/plate-number-77-ascending-an-incline.json/canvas/static/placeholder/page/1",
            "type": "AnnotationPage",
            "items": [
              {
                "id": "https://nulib-ds.github.io/muybridge/iiif/plate-number-77-ascending-an-incline.json/canvas/static/placeholder/page/1/annotation/1",
                "type": "Annotation",
                "motivation": "painting",
                "body": {
                  "id": "https://api.nga.gov/iiif/63eb96e1-8e5e-46b8-99ba-822824225e86/full/800,/0/default.jpg",
                  "type": "Image",
                  "format": "image/jpeg",
                  "width": 800,
                  "height": 451
                },
                "target": "https://nulib-ds.github.io/muybridge/iiif/plate-number-77-ascending-an-incline.json/canvas/static/placeholder"
              }
            ]
          }
        ]
      },
      "items": [
        {
          "id": "https://nulib-ds.github.io/muybridge/iiif/plate-number-77-ascending-an-incline.json/canvas/static/page/1",
          "type": "AnnotationPage",
          "items": [
            {
              "id": "https://nulib-ds.github.io/muybridge/iiif/plate-number-77-ascending-an-incline.json/canvas/static/page/1/annotation/1",
              "type": "Annotation",
              "motivation": "painting",
              "body": {
                "id": "https://api.nga.gov/iiif/63eb96e1-8e5e-46b8-99ba-822824225e86/full/full/0/default.jpg",
                "type": "Image",
                "format": "image/jpeg",
                "height": 2148,
                "width": 3814,
                "service": [
                  {
                    "id": "https://api.nga.gov/iiif/63eb96e1-8e5e-46b8-99ba-822824225e86",
                    "type": "ImageService2",
                    "profile": "level2"
                  }
                ]
              },
              "target": "https://nulib-ds.github.io/muybridge/iiif/plate-number-77-ascending-an-incline.json/canvas/static"
            }
          ]
        }
      ]
    }
  ]
}
