{
  "@context": "https://iiif.io/api/presentation/3/context.json",
  "id": "http://localhost:5001/iiif/plate-number-131-descending-stairs-waving-hand.json",
  "type": "Manifest",
  "label": {
    "en": [
      "Plate Number 131. Descending stairs, waving hand"
    ]
  },
  "behavior": [
    "repeat",
    "auto-advance"
  ],
  "metadata": [
    {
      "label": {
        "en": [
          "Date"
        ]
      },
      "value": {
        "en": [
          "1887"
        ]
      }
    },
    {
      "label": {
        "en": [
          "Plate Number"
        ]
      },
      "value": {
        "en": [
          "131"
        ]
      }
    },
    {
      "label": {
        "en": [
          "Frames"
        ]
      },
      "value": {
        "en": [
          "24"
        ]
      }
    },
    {
      "label": {
        "en": [
          "Provider"
        ]
      },
      "value": {
        "en": [
          "National Gallery of Art"
        ]
      }
    }
  ],
  "thumbnail": [
    {
      "id": "http://localhost:5001/images/thumbnails/plate-number-131-descending-stairs-waving-hand.gif",
      "type": "Image",
      "format": "image/gif"
    }
  ],
  "items": [
    {
      "id": "http://localhost:5001/iiif/plate-number-131-descending-stairs-waving-hand.json/canvas/animation",
      "type": "Canvas",
      "label": {
        "en": [
          "Plate Number 131. Descending stairs, waving hand"
        ]
      },
      "height": 896,
      "width": 327,
      "duration": 2.4,
      "placeholderCanvas": {
        "id": "http://localhost:5001/iiif/plate-number-131-descending-stairs-waving-hand.json/canvas/animation/placeholder",
        "type": "Canvas",
        "width": 327,
        "height": 896,
        "items": [
          {
            "id": "http://localhost:5001/iiif/plate-number-131-descending-stairs-waving-hand.json/canvas/animation/placeholder/page/1",
            "type": "AnnotationPage",
            "items": [
              {
                "id": "http://localhost:5001/iiif/plate-number-131-descending-stairs-waving-hand.json/canvas/animation/placeholder/page/1/annotation/1",
                "type": "Annotation",
                "motivation": "painting",
                "body": {
                  "id": "http://localhost:5001/images/thumbnails/plate-number-131-descending-stairs-waving-hand.gif",
                  "type": "Image",
                  "format": "image/gif",
                  "width": 327,
                  "height": 896
                },
                "target": "http://localhost:5001/iiif/plate-number-131-descending-stairs-waving-hand.json/canvas/animation/placeholder"
              }
            ]
          }
        ]
      },
      "items": [
        {
          "id": "http://localhost:5001/iiif/plate-number-131-descending-stairs-waving-hand.json/canvas/animation/page/1",
          "type": "AnnotationPage",
          "items": [
            {
              "id": "http://localhost:5001/iiif/plate-number-131-descending-stairs-waving-hand.json/canvas/animation/page/1/annotation/1",
              "type": "Annotation",
              "motivation": "painting",
              "label": {
                "en": [
                  "1"
                ]
              },
              "body": {
                "id": "https://api.nga.gov/iiif/47cfc5d7-426c-4656-819a-d984f48b08bb/pct:0.6802,1.3650,7.8521,46.7567/full/0/default.jpg",
                "type": "Image",
                "format": "image/jpeg",
                "height": 896,
                "width": 327
              },
              "target": "http://localhost:5001/iiif/plate-number-131-descending-stairs-waving-hand.json/canvas/animation#t=0,0.1"
            },
            {
              "id": "http://localhost:5001/iiif/plate-number-131-descending-stairs-waving-hand.json/canvas/animation/page/1/annotation/2",
              "type": "Annotation",
              "motivation": "painting",
              "label": {
                "en": [
                  "2"
                ]
              },
              "body": {
                "id": "https://api.nga.gov/iiif/47cfc5d7-426c-4656-819a-d984f48b08bb/pct:8.9168,1.3650,7.8521,46.7567/full/0/default.jpg",
                "type": "Image",
                "format": "image/jpeg",
                "height": 896,
                "width": 327
              },
              "target": "http://localhost:5001/iiif/plate-number-131-descending-stairs-waving-hand.json/canvas/animation#t=0.1,0.2"
            },
            {
              "id": "http://localhost:5001/iiif/plate-number-131-descending-stairs-waving-hand.json/canvas/animation/page/1/annotation/3",
              "type": "Annotation",
              "motivation": "painting",
              "label": {
                "en": [
                  "3"
                ]
              },
              "body": {
                "id": "https://api.nga.gov/iiif/47cfc5d7-426c-4656-819a-d984f48b08bb/pct:17.1534,1.3650,7.8521,46.7567/full/0/default.jpg",
                "type": "Image",
                "format": "image/jpeg",
                "height": 896,
                "width": 327
              },
              "target": "http://localhost:5001/iiif/plate-number-131-descending-stairs-waving-hand.json/canvas/animation#t=0.2,0.3"
            },
            {
              "id": "http://localhost:5001/iiif/plate-number-131-descending-stairs-waving-hand.json/canvas/animation/page/1/annotation/4",
              "type": "Annotation",
              "motivation": "painting",
              "label": {
                "en": [
                  "4"
                ]
              },
              "body": {
                "id": "https://api.nga.gov/iiif/47cfc5d7-426c-4656-819a-d984f48b08bb/pct:25.3900,1.3650,7.8521,46.7567/full/0/default.jpg",
                "type": "Image",
                "format": "image/jpeg",
                "height": 896,
                "width": 327
              },
              "target": "http://localhost:5001/iiif/plate-number-131-descending-stairs-waving-hand.json/canvas/animation#t=0.3,0.4"
            },
            {
              "id": "http://localhost:5001/iiif/plate-number-131-descending-stairs-waving-hand.json/canvas/animation/page/1/annotation/5",
              "type": "Annotation",
              "motivation": "painting",
              "label": {
                "en": [
                  "5"
                ]
              },
              "body": {
                "id": "https://api.nga.gov/iiif/47cfc5d7-426c-4656-819a-d984f48b08bb/pct:33.6266,1.3650,7.8521,46.7567/full/0/default.jpg",
                "type": "Image",
                "format": "image/jpeg",
                "height": 896,
                "width": 327
              },
              "target": "http://localhost:5001/iiif/plate-number-131-descending-stairs-waving-hand.json/canvas/animation#t=0.4,0.5"
            },
            {
              "id": "http://localhost:5001/iiif/plate-number-131-descending-stairs-waving-hand.json/canvas/animation/page/1/annotation/6",
              "type": "Annotation",
              "motivation": "painting",
              "label": {
                "en": [
                  "6"
                ]
              },
              "body": {
                "id": "https://api.nga.gov/iiif/47cfc5d7-426c-4656-819a-d984f48b08bb/pct:41.8632,1.3650,7.8521,46.7567/full/0/default.jpg",
                "type": "Image",
                "format": "image/jpeg",
                "height": 896,
                "width": 327
              },
              "target": "http://localhost:5001/iiif/plate-number-131-descending-stairs-waving-hand.json/canvas/animation#t=0.5,0.6"
            },
            {
              "id": "http://localhost:5001/iiif/plate-number-131-descending-stairs-waving-hand.json/canvas/animation/page/1/annotation/7",
              "type": "Annotation",
              "motivation": "painting",
              "label": {
                "en": [
                  "7"
                ]
              },
              "body": {
                "id": "https://api.nga.gov/iiif/47cfc5d7-426c-4656-819a-d984f48b08bb/pct:50.0998,1.3650,7.8521,46.7567/full/0/default.jpg",
                "type": "Image",
                "format": "image/jpeg",
                "height": 896,
                "width": 327
              },
              "target": "http://localhost:5001/iiif/plate-number-131-descending-stairs-waving-hand.json/canvas/animation#t=0.6,0.7"
            },
            {
              "id": "http://localhost:5001/iiif/plate-number-131-descending-stairs-waving-hand.json/canvas/animation/page/1/annotation/8",
              "type": "Annotation",
              "motivation": "painting",
              "label": {
                "en": [
                  "8"
                ]
              },
              "body": {
                "id": "https://api.nga.gov/iiif/47cfc5d7-426c-4656-819a-d984f48b08bb/pct:58.3364,1.3650,7.8521,46.7567/full/0/default.jpg",
                "type": "Image",
                "format": "image/jpeg",
                "height": 896,
                "width": 327
              },
              "target": "http://localhost:5001/iiif/plate-number-131-descending-stairs-waving-hand.json/canvas/animation#t=0.7,0.8"
            },
            {
              "id": "http://localhost:5001/iiif/plate-number-131-descending-stairs-waving-hand.json/canvas/animation/page/1/annotation/9",
              "type": "Annotation",
              "motivation": "painting",
              "label": {
                "en": [
                  "9"
                ]
              },
              "body": {
                "id": "https://api.nga.gov/iiif/47cfc5d7-426c-4656-819a-d984f48b08bb/pct:66.5730,1.3650,7.8521,46.7567/full/0/default.jpg",
                "type": "Image",
                "format": "image/jpeg",
                "height": 896,
                "width": 327
              },
              "target": "http://localhost:5001/iiif/plate-number-131-descending-stairs-waving-hand.json/canvas/animation#t=0.8,0.9"
            },
            {
              "id": "http://localhost:5001/iiif/plate-number-131-descending-stairs-waving-hand.json/canvas/animation/page/1/annotation/10",
              "type": "Annotation",
              "motivation": "painting",
              "label": {
                "en": [
                  "10"
                ]
              },
              "body": {
                "id": "https://api.nga.gov/iiif/47cfc5d7-426c-4656-819a-d984f48b08bb/pct:74.8096,1.3650,7.8521,46.7567/full/0/default.jpg",
                "type": "Image",
                "format": "image/jpeg",
                "height": 896,
                "width": 327
              },
              "target": "http://localhost:5001/iiif/plate-number-131-descending-stairs-waving-hand.json/canvas/animation#t=0.9,1"
            },
            {
              "id": "http://localhost:5001/iiif/plate-number-131-descending-stairs-waving-hand.json/canvas/animation/page/1/annotation/11",
              "type": "Annotation",
              "motivation": "painting",
              "label": {
                "en": [
                  "11"
                ]
              },
              "body": {
                "id": "https://api.nga.gov/iiif/47cfc5d7-426c-4656-819a-d984f48b08bb/pct:83.0462,1.3650,7.8521,46.7567/full/0/default.jpg",
                "type": "Image",
                "format": "image/jpeg",
                "height": 896,
                "width": 327
              },
              "target": "http://localhost:5001/iiif/plate-number-131-descending-stairs-waving-hand.json/canvas/animation#t=1,1.1"
            },
            {
              "id": "http://localhost:5001/iiif/plate-number-131-descending-stairs-waving-hand.json/canvas/animation/page/1/annotation/12",
              "type": "Annotation",
              "motivation": "painting",
              "label": {
                "en": [
                  "12"
                ]
              },
              "body": {
                "id": "https://api.nga.gov/iiif/47cfc5d7-426c-4656-819a-d984f48b08bb/pct:91.2828,1.3650,7.8521,46.7567/full/0/default.jpg",
                "type": "Image",
                "format": "image/jpeg",
                "height": 896,
                "width": 327
              },
              "target": "http://localhost:5001/iiif/plate-number-131-descending-stairs-waving-hand.json/canvas/animation#t=1.1,1.2"
            },
            {
              "id": "http://localhost:5001/iiif/plate-number-131-descending-stairs-waving-hand.json/canvas/animation/page/1/annotation/13",
              "type": "Annotation",
              "motivation": "painting",
              "label": {
                "en": [
                  "13"
                ]
              },
              "body": {
                "id": "https://api.nga.gov/iiif/47cfc5d7-426c-4656-819a-d984f48b08bb/pct:0.7013,52.9349,7.8099,45.8399/full/0/default.jpg",
                "type": "Image",
                "format": "image/jpeg",
                "height": 878,
                "width": 325
              },
              "target": "http://localhost:5001/iiif/plate-number-131-descending-stairs-waving-hand.json/canvas/animation#t=1.2,1.3"
            },
            {
              "id": "http://localhost:5001/iiif/plate-number-131-descending-stairs-waving-hand.json/canvas/animation/page/1/annotation/14",
              "type": "Annotation",
              "motivation": "painting",
              "label": {
                "en": [
                  "14"
                ]
              },
              "body": {
                "id": "https://api.nga.gov/iiif/47cfc5d7-426c-4656-819a-d984f48b08bb/pct:8.9438,52.9349,7.8099,45.8399/full/0/default.jpg",
                "type": "Image",
                "format": "image/jpeg",
                "height": 878,
                "width": 325
              },
              "target": "http://localhost:5001/iiif/plate-number-131-descending-stairs-waving-hand.json/canvas/animation#t=1.3,1.4"
            },
            {
              "id": "http://localhost:5001/iiif/plate-number-131-descending-stairs-waving-hand.json/canvas/animation/page/1/annotation/15",
              "type": "Annotation",
              "motivation": "painting",
              "label": {
                "en": [
                  "15"
                ]
              },
              "body": {
                "id": "https://api.nga.gov/iiif/47cfc5d7-426c-4656-819a-d984f48b08bb/pct:17.1862,52.9349,7.8099,45.8399/full/0/default.jpg",
                "type": "Image",
                "format": "image/jpeg",
                "height": 878,
                "width": 325
              },
              "target": "http://localhost:5001/iiif/plate-number-131-descending-stairs-waving-hand.json/canvas/animation#t=1.4,1.5"
            },
            {
              "id": "http://localhost:5001/iiif/plate-number-131-descending-stairs-waving-hand.json/canvas/animation/page/1/annotation/16",
              "type": "Annotation",
              "motivation": "painting",
              "label": {
                "en": [
                  "16"
                ]
              },
              "body": {
                "id": "https://api.nga.gov/iiif/47cfc5d7-426c-4656-819a-d984f48b08bb/pct:25.4287,52.9349,7.8099,45.8399/full/0/default.jpg",
                "type": "Image",
                "format": "image/jpeg",
                "height": 878,
                "width": 325
              },
              "target": "http://localhost:5001/iiif/plate-number-131-descending-stairs-waving-hand.json/canvas/animation#t=1.5,1.6"
            },
            {
              "id": "http://localhost:5001/iiif/plate-number-131-descending-stairs-waving-hand.json/canvas/animation/page/1/annotation/17",
              "type": "Annotation",
              "motivation": "painting",
              "label": {
                "en": [
                  "17"
                ]
              },
              "body": {
                "id": "https://api.nga.gov/iiif/47cfc5d7-426c-4656-819a-d984f48b08bb/pct:33.6711,52.9349,7.8099,45.8399/full/0/default.jpg",
                "type": "Image",
                "format": "image/jpeg",
                "height": 878,
                "width": 325
              },
              "target": "http://localhost:5001/iiif/plate-number-131-descending-stairs-waving-hand.json/canvas/animation#t=1.6,1.7"
            },
            {
              "id": "http://localhost:5001/iiif/plate-number-131-descending-stairs-waving-hand.json/canvas/animation/page/1/annotation/18",
              "type": "Annotation",
              "motivation": "painting",
              "label": {
                "en": [
                  "18"
                ]
              },
              "body": {
                "id": "https://api.nga.gov/iiif/47cfc5d7-426c-4656-819a-d984f48b08bb/pct:41.9136,52.9349,7.8099,45.8399/full/0/default.jpg",
                "type": "Image",
                "format": "image/jpeg",
                "height": 878,
                "width": 325
              },
              "target": "http://localhost:5001/iiif/plate-number-131-descending-stairs-waving-hand.json/canvas/animation#t=1.7,1.8"
            },
            {
              "id": "http://localhost:5001/iiif/plate-number-131-descending-stairs-waving-hand.json/canvas/animation/page/1/annotation/19",
              "type": "Annotation",
              "motivation": "painting",
              "label": {
                "en": [
                  "19"
                ]
              },
              "body": {
                "id": "https://api.nga.gov/iiif/47cfc5d7-426c-4656-819a-d984f48b08bb/pct:50.1560,52.9349,7.8099,45.8399/full/0/default.jpg",
                "type": "Image",
                "format": "image/jpeg",
                "height": 878,
                "width": 325
              },
              "target": "http://localhost:5001/iiif/plate-number-131-descending-stairs-waving-hand.json/canvas/animation#t=1.8,1.9"
            },
            {
              "id": "http://localhost:5001/iiif/plate-number-131-descending-stairs-waving-hand.json/canvas/animation/page/1/annotation/20",
              "type": "Annotation",
              "motivation": "painting",
              "label": {
                "en": [
                  "20"
                ]
              },
              "body": {
                "id": "https://api.nga.gov/iiif/47cfc5d7-426c-4656-819a-d984f48b08bb/pct:58.3985,52.9349,7.8099,45.8399/full/0/default.jpg",
                "type": "Image",
                "format": "image/jpeg",
                "height": 878,
                "width": 325
              },
              "target": "http://localhost:5001/iiif/plate-number-131-descending-stairs-waving-hand.json/canvas/animation#t=1.9,2"
            },
            {
              "id": "http://localhost:5001/iiif/plate-number-131-descending-stairs-waving-hand.json/canvas/animation/page/1/annotation/21",
              "type": "Annotation",
              "motivation": "painting",
              "label": {
                "en": [
                  "21"
                ]
              },
              "body": {
                "id": "https://api.nga.gov/iiif/47cfc5d7-426c-4656-819a-d984f48b08bb/pct:66.6409,52.9349,7.8099,45.8399/full/0/default.jpg",
                "type": "Image",
                "format": "image/jpeg",
                "height": 878,
                "width": 325
              },
              "target": "http://localhost:5001/iiif/plate-number-131-descending-stairs-waving-hand.json/canvas/animation#t=2,2.1"
            },
            {
              "id": "http://localhost:5001/iiif/plate-number-131-descending-stairs-waving-hand.json/canvas/animation/page/1/annotation/22",
              "type": "Annotation",
              "motivation": "painting",
              "label": {
                "en": [
                  "22"
                ]
              },
              "body": {
                "id": "https://api.nga.gov/iiif/47cfc5d7-426c-4656-819a-d984f48b08bb/pct:74.8834,52.9349,7.8099,45.8399/full/0/default.jpg",
                "type": "Image",
                "format": "image/jpeg",
                "height": 878,
                "width": 325
              },
              "target": "http://localhost:5001/iiif/plate-number-131-descending-stairs-waving-hand.json/canvas/animation#t=2.1,2.2"
            },
            {
              "id": "http://localhost:5001/iiif/plate-number-131-descending-stairs-waving-hand.json/canvas/animation/page/1/annotation/23",
              "type": "Annotation",
              "motivation": "painting",
              "label": {
                "en": [
                  "23"
                ]
              },
              "body": {
                "id": "https://api.nga.gov/iiif/47cfc5d7-426c-4656-819a-d984f48b08bb/pct:83.1258,52.9349,7.8099,45.8399/full/0/default.jpg",
                "type": "Image",
                "format": "image/jpeg",
                "height": 878,
                "width": 325
              },
              "target": "http://localhost:5001/iiif/plate-number-131-descending-stairs-waving-hand.json/canvas/animation#t=2.2,2.3"
            },
            {
              "id": "http://localhost:5001/iiif/plate-number-131-descending-stairs-waving-hand.json/canvas/animation/page/1/annotation/24",
              "type": "Annotation",
              "motivation": "painting",
              "label": {
                "en": [
                  "24"
                ]
              },
              "body": {
                "id": "https://api.nga.gov/iiif/47cfc5d7-426c-4656-819a-d984f48b08bb/pct:91.3683,52.9349,7.8099,45.8399/full/0/default.jpg",
                "type": "Image",
                "format": "image/jpeg",
                "height": 878,
                "width": 325
              },
              "target": "http://localhost:5001/iiif/plate-number-131-descending-stairs-waving-hand.json/canvas/animation#t=2.3,2.4"
            }
          ]
        }
      ]
    },
    {
      "id": "http://localhost:5001/iiif/plate-number-131-descending-stairs-waving-hand.json/canvas/static",
      "type": "Canvas",
      "label": {
        "en": [
          "Plate Number 131. Descending stairs, waving hand"
        ]
      },
      "height": 1916,
      "width": 4161,
      "placeholderCanvas": {
        "id": "http://localhost:5001/iiif/plate-number-131-descending-stairs-waving-hand.json/canvas/static/placeholder",
        "type": "Canvas",
        "width": 800,
        "height": 368,
        "items": [
          {
            "id": "http://localhost:5001/iiif/plate-number-131-descending-stairs-waving-hand.json/canvas/static/placeholder/page/1",
            "type": "AnnotationPage",
            "items": [
              {
                "id": "http://localhost:5001/iiif/plate-number-131-descending-stairs-waving-hand.json/canvas/static/placeholder/page/1/annotation/1",
                "type": "Annotation",
                "motivation": "painting",
                "body": {
                  "id": "https://api.nga.gov/iiif/47cfc5d7-426c-4656-819a-d984f48b08bb/full/800,/0/default.jpg",
                  "type": "Image",
                  "format": "image/jpeg",
                  "width": 800,
                  "height": 368
                },
                "target": "http://localhost:5001/iiif/plate-number-131-descending-stairs-waving-hand.json/canvas/static/placeholder"
              }
            ]
          }
        ]
      },
      "items": [
        {
          "id": "http://localhost:5001/iiif/plate-number-131-descending-stairs-waving-hand.json/canvas/static/page/1",
          "type": "AnnotationPage",
          "items": [
            {
              "id": "http://localhost:5001/iiif/plate-number-131-descending-stairs-waving-hand.json/canvas/static/page/1/annotation/1",
              "type": "Annotation",
              "motivation": "painting",
              "body": {
                "id": "https://api.nga.gov/iiif/47cfc5d7-426c-4656-819a-d984f48b08bb/full/full/0/default.jpg",
                "type": "Image",
                "format": "image/jpeg",
                "height": 1916,
                "width": 4161,
                "service": [
                  {
                    "id": "https://api.nga.gov/iiif/47cfc5d7-426c-4656-819a-d984f48b08bb",
                    "type": "ImageService2",
                    "profile": "level2"
                  }
                ]
              },
              "target": "http://localhost:5001/iiif/plate-number-131-descending-stairs-waving-hand.json/canvas/static"
            }
          ]
        }
      ]
    }
  ]
}